cPragmaModifier
