Metadata-Version: 1.0
Name: cPragmaModifier
Version: 1.0.1
Summary: Openmp C pragma Modifier in Source Code
Home-page: https://github.com/PasinduSenanayake/Rigel-FYP/tree/cPragmaModifierpackage
Author: Rigel
Author-email: praveen.14@cse.mrt.ac.lk
License: MIT
Platform: UNKNOWN
